MANIFEST.in
README.RST
README.md
setup.py
py_win_keyboard_layout/__init__.py
py_win_keyboard_layout.egg-info/PKG-INFO
py_win_keyboard_layout.egg-info/SOURCES.txt
py_win_keyboard_layout.egg-info/dependency_links.txt
py_win_keyboard_layout.egg-info/not-zip-safe
py_win_keyboard_layout.egg-info/requires.txt
py_win_keyboard_layout.egg-info/top_level.txt