Metadata-Version: 1.1
Name: py-win-keyboard-layout
Version: 0.2
Summary: Interaction with keyboard layout on windows
Home-page: http://github.com/Lex98/py_win_keyboard_layout
Author: Lex98
Author-email: UNKNOWN
License: MIT
Keywords: windows keyboard layout language
Platform: UNKNOWN
Classifier: Development Status :: 3 - Alpha
Classifier: License :: OSI Approved :: MIT License
Classifier: Programming Language :: Python :: 3.5
Classifier: Environment :: Win32 (MS Windows)
Classifier: Operating System :: Microsoft :: Windows :: Windows 7
Classifier: Topic :: Utilities
Classifier: Topic :: Software Development :: Libraries :: Python Modules
